devpi_tools/__init__.py
devpi_tools/models.py
devpi_tools-0.5.3.dist-info/LICENSE
devpi_tools-0.5.3.dist-info/METADATA
devpi_tools-0.5.3.dist-info/WHEEL
devpi_tools-0.5.3.dist-info/top_level.txt
devpi_tools-0.5.3.dist-info/RECORD
