Metadata-Version: 2.1
Name: devpi-tools
Version: 0.5.3
Summary: library for interacting with devpi servers via web API
Home-page: https://github.com/bcicen/devpi-tools
Author: Bradley Cicenas
Author-email: bradley@vektor.nyc
License: http://opensource.org/licenses/MIT
Keywords: devpi pypi packaging devops
Platform: UNKNOWN
Classifier: Natural Language :: English
Classifier: Programming Language :: Python
Classifier: Intended Audience :: Developers
Classifier: Programming Language :: Python :: 2
Classifier: Programming Language :: Python :: 3
Classifier: Programming Language :: Python :: 3.7
Classifier: License :: OSI Approved :: MIT License 
Requires-Dist: requests (>=2.9.1)
